Metadata-Version: 2.1
Name: remote-ikernel-mosh
Version: 0.4.2
Summary: Running IPython kernels through batch queues. A fork of the original that supports mosh.
Home-page: https://bitbucket.org/tdaff/remote_ikernel
Author: Tom Daff
Author-email: tdd20@cam.ac.uk
License: BSD
Platform: UNKNOWN
Classifier: Programming Language :: Python :: 2
Classifier: Programming Language :: Python :: 3
Classifier: Framework :: IPython
Classifier: License :: OSI Approved :: BSD License
License-File: LICENSE.txt
